torchgeneric/nn/__init__.py
torchgeneric/nn/dlu.py
torchgeneric/nn/glu.py
torchgeneric/nn/sau.py
torchgeneric/nn/slu.py
torchgeneric/optim/__init__.py
torchgeneric/optim/cgd.py
torchgeneric-0.2.1.dist-info/METADATA
torchgeneric-0.2.1.dist-info/WHEEL
torchgeneric-0.2.1.dist-info/licenses/LICENSE
torchgeneric-0.2.1.dist-info/RECORD
