Metadata-Version: 2.4
Name: torchgeneric
Version: 0.2.1
Summary: Generic Artificial Learning Algorithms
License: Apache-2.0
License-File: LICENSE
Author: eric-hermosis
Author-email: eric.hermosis@gmail.com
Requires-Python: >=3.12
Classifier: License :: OSI Approved :: Apache Software License
Classifier: Programming Language :: Python :: 3
Classifier: Programming Language :: Python :: 3.12
Classifier: Programming Language :: Python :: 3.13
Classifier: Programming Language :: Python :: 3.14
